regret/__init__.py
regret/_api.py
regret/_inspect.py
regret/_sphinx.py
regret/_warnings.py
regret/emitted.py
regret/testing.py
regret/typing.py
regret/tests/__init__.py
regret/tests/test_api.py
regret/tests/test_integration.py
regret/tests/test_testing.py
regret-2024.2.2.dist-info/METADATA
regret-2024.2.2.dist-info/WHEEL
regret-2024.2.2.dist-info/licenses/COPYING
regret-2024.2.2.dist-info/RECORD
