Metadata-Version: 2.1
Name: regret
Version: 2024.2.2
Summary: You made a thing, but now you wish it'd go away... Deprecations, a love story.
Project-URL: Documentation, https://regret.readthedocs.io/
Project-URL: Homepage, https://github.com/Julian/regret
Project-URL: Issues, https://github.com/Julian/regret/issues/
Project-URL: Funding, https://github.com/sponsors/Julian
Project-URL: Source, https://github.com/Julian/regret
Author-email: Julian Berman <Julian+regret@GrayVines.com>
License-File: COPYING
Keywords: deprecation,deprecations,maintenance,regret,tooling
Classifier: Development Status :: 4 - Beta
Classifier: Intended Audience :: Developers
Classifier: License :: OSI Approved :: MIT License
Classifier: Operating System :: OS Independent
Classifier: Programming Language :: Python
Classifier: Programming Language :: Python :: 3.8
Classifier: Programming Language :: Python :: 3.9
Classifier: Programming Language :: Python :: 3.10
Classifier: Programming Language :: Python :: 3.11
Classifier: Programming Language :: Python :: 3.12
Classifier: Programming Language :: Python :: Implementation :: CPython
Classifier: Programming Language :: Python :: Implementation :: PyPy
Requires-Python: >=3.8
Requires-Dist: attrs
